common_utils/__init__.py
common_utils/cloud/__init__.py
common_utils/cloud/base.py
common_utils/cloud/aws/__init__.py
common_utils/cloud/aws/base.py
common_utils/cloud/aws/ec2.py
common_utils/cloud/aws/s3.py
common_utils/cloud/gcp/__init__.py
common_utils/cloud/gcp/database/__init__.py
common_utils/cloud/gcp/database/bigquery.py
common_utils/cloud/gcp/storage/__init__.py
common_utils/cloud/gcp/storage/gcs.py
common_utils/core/__init__.py
common_utils/core/artifacts.py
common_utils/core/base.py
common_utils/core/common.py
common_utils/core/file_system_utils.py
common_utils/core/logger.py
common_utils/core/decorators/decorators.py
common_utils/core/decorators/timer.py
common_utils/data_validator/base.py
common_utils/data_validator/core.py
common_utils/experiment_tracking/promoter/base.py
common_utils/experiment_tracking/promoter/core.py
common_utils/orchestrator/base.py
common_utils/orchestrator/core.py
common_utils/tests/core.py
common_utils/versioning/dvc/base.py
common_utils/versioning/dvc/core.py
common_utils/versioning/git/base.py
common_utils/versioning/git/core.py
gaohn_common_utils-0.0.112.dist-info/LICENSE
gaohn_common_utils-0.0.112.dist-info/METADATA
gaohn_common_utils-0.0.112.dist-info/WHEEL
gaohn_common_utils-0.0.112.dist-info/top_level.txt
gaohn_common_utils-0.0.112.dist-info/RECORD
