Metadata-Version: 2.1
Name: gaohn-common-utils
Version: 0.0.112
Summary: A small utility package
Author-email: Gao Hongnan <hongnangao@gmail.com>
Project-URL: Homepage, https://github.com/gao-hongnan/common-utils
Project-URL: Bug Tracker, https://github.com/gao-hongnan/common-utils/issues
Classifier: Programming Language :: Python :: 3
Classifier: License :: OSI Approved :: MIT License
Classifier: Operating System :: OS Independent
Requires-Python: >=3.7
License-File: LICENSE
Requires-Dist: awscli
Requires-Dist: db-dtypes <2.0,>=1.1
Requires-Dist: google-cloud-bigquery <4.0,>=3.10
Requires-Dist: google-cloud-storage <3.0,>=2.8
Requires-Dist: ipython
Requires-Dist: numpy <2.0,>=1.24
Requires-Dist: pandas <2.0,>=1.5
Requires-Dist: prettytable <4.0,>=3.7
Requires-Dist: pydantic <3.0,>=2.0
Requires-Dist: python-dotenv <2.0,>=1.0
Requires-Dist: pytz <2024,>=2023
Requires-Dist: requests <3.0,>=2.28
Requires-Dist: rich <14.0,>=13.3
Requires-Dist: tabulate <1.0,>=0.9
Requires-Dist: torch <3.0,>=2.0
Requires-Dist: torchaudio <3.0,>=2.0
Requires-Dist: torchvision <1.0,>=0.15
Provides-Extra: dev
Requires-Dist: bandit <2.0,>=1.7 ; extra == 'dev'
Requires-Dist: black <24.0,>=23.3 ; extra == 'dev'
Requires-Dist: colorama <1.0,>=0.4 ; extra == 'dev'
Requires-Dist: coverage <8.0,>=7.0 ; extra == 'dev'
Requires-Dist: isort <6.0,>=5.12 ; extra == 'dev'
Requires-Dist: mypy <2.0,>=1.3 ; extra == 'dev'
Requires-Dist: pylint <3.0,>=2.17 ; extra == 'dev'
Requires-Dist: pytest <7.0,>=6.2 ; extra == 'dev'
Requires-Dist: pytest-cov <5.0,>=4.0 ; extra == 'dev'
Requires-Dist: toml <1.0,>=0.10 ; extra == 'dev'
